fsPacker/__init__.py
fsPacker/_fspacker.pyi
fsPacker/fallback.py
fsPacker/py.typed
python_fspacker-0.2.1.dist-info/LICENSE.md
python_fspacker-0.2.1.dist-info/METADATA
python_fspacker-0.2.1.dist-info/WHEEL
python_fspacker-0.2.1.dist-info/top_level.txt
python_fspacker-0.2.1.dist-info/RECORD
